john/__init__.py
john/factory.py
john/tdd.py
john/test_case.py
john-0.1.6.dist-info/LICENSE
john-0.1.6.dist-info/METADATA
john-0.1.6.dist-info/WHEEL
john-0.1.6.dist-info/RECORD
